delfies/SAM_utils.py
delfies/__init__.py
delfies/breakpoint_foci.py
delfies/breakpoint_sequences.py
delfies/delfies.py
delfies/interval_utils.py
delfies/seq_utils.py
delfies/telomere_utils.py
delfies-0.11.0.dist-info/METADATA
delfies-0.11.0.dist-info/WHEEL
delfies-0.11.0.dist-info/entry_points.txt
delfies-0.11.0.dist-info/licenses/LICENSE
delfies-0.11.0.dist-info/RECORD
