Metadata-Version: 2.4
Name: delfies
Version: 0.11.0
Summary: delfies is a tool for the detection of DNA Elimination breakpoints
Author-email: Brice Letcher <brice.letcher@ens-lyon.fr>
License-Expression: MIT
License-File: LICENSE
Requires-Python: >=3.9.0
Requires-Dist: click>=8.1.7
Requires-Dist: datasci-bricoletc>=0.1.1
Requires-Dist: edlib>=1.3.9
Requires-Dist: pybedtools>=0.9.1
Requires-Dist: pyfastx>=2.1.0
Requires-Dist: pysam>=0.22.0
Requires-Dist: rich-click>=1.7.3
